txcan/__init__.py
txcan/_version.py
txcan/cli.py
txcan/core.py
txcan-2020.10.2.dist-info/METADATA
txcan-2020.10.2.dist-info/WHEEL
txcan-2020.10.2.dist-info/entry_points.txt
txcan-2020.10.2.dist-info/top_level.txt
txcan-2020.10.2.dist-info/RECORD
